{
    "name": "Global Information",
    "numberOfRequests": {
        "total": 6000,
        "ok": 0,
        "ko": 6000
    },
    "minResponseTime": {
        "total": 60,
        "ok": 0,
        "ko": 60
    },
    "maxResponseTime": {
        "total": 1097,
        "ok": 0,
        "ko": 1097
    },
    "meanResponseTime": {
        "total": 66,
        "ok": 0,
        "ko": 66
    },
    "standardDeviation": {
        "total": 48,
        "ok": 0,
        "ko": 48
    },
    "percentiles1": {
        "total": 62,
        "ok": 0,
        "ko": 62
    },
    "percentiles2": {
        "total": 63,
        "ok": 0,
        "ko": 63
    },
    "percentiles3": {
        "total": 70,
        "ok": 0,
        "ko": 70
    },
    "percentiles4": {
        "total": 77,
        "ok": 0,
        "ko": 77
    },
    "group1": {
        "name": "t < 800 ms",
        "count": 0,
        "percentage": 0
    },
    "group2": {
        "name": "800 ms < t < 1200 ms",
        "count": 0,
        "percentage": 0
    },
    "group3": {
        "name": "t > 1200 ms",
        "count": 0,
        "percentage": 0
    },
    "group4": {
        "name": "failed",
        "count": 6000,
        "percentage": 100
    },
    "meanNumberOfRequestsPerSecond": {
        "total": 75.9493670886076,
        "ok": 0,
        "ko": 75.9493670886076
    }
}